wsserver_malbizer-1.0.6.data/scripts/wsclient-malbizer.py
wsserver_malbizer-1.0.6.data/scripts/wssend-malbizer.py
wsserver_malbizer-1.0.6.data/scripts/wsserver-malbizer.py
wsservermalbizer/__init__.py
wsservermalbizer/logmessage.py
wsservermalbizer/websocketclient.py
wsservermalbizer/websocketmessage.py
wsservermalbizer/websocketserver.py
wsserver_malbizer-1.0.6.dist-info/METADATA
wsserver_malbizer-1.0.6.dist-info/WHEEL
wsserver_malbizer-1.0.6.dist-info/top_level.txt
wsserver_malbizer-1.0.6.dist-info/RECORD
