Metadata-Version: 2.1
Name: wsserver-malbizer
Version: 1.0.6
Summary: Websocket Server for python
Home-page: UNKNOWN
Author: Anderson Souza
Author-email: anderson@malbizer.com.br
License: UNKNOWN
Keywords: python,websocket,server
Platform: UNKNOWN
Classifier: Development Status :: 3 - Alpha
Classifier: Intended Audience :: Education
Classifier: Programming Language :: Python :: 2
Classifier: Programming Language :: Python :: 3
Classifier: Operating System :: MacOS :: MacOS X
Classifier: Operating System :: Microsoft :: Windows
Requires-Dist: websockets (==9.1)
Requires-Dist: websocket-client (==1.1.0)
